edc_model_form/__init__.py
edc_model_form/apps.py
edc_model_form/urls.py
edc_model_form/utils.py
edc_model_form/mixins/__init__.py
edc_model_form/mixins/base_model_form_mixin.py
edc_model_form/mixins/inline_model_form_mixin.py
edc_model_form/mixins/report_datetime_modelform_mixin.py
edc_model_form/tests/__init__.py
edc_model_form/tests/test_settings.py
edc_model_form/tests/etc/user-aes-local.key
edc_model_form/tests/etc/user-aes-restricted.key
edc_model_form/tests/etc/user-rsa-local-private.pem
edc_model_form/tests/etc/user-rsa-local-public.pem
edc_model_form/tests/etc/user-rsa-restricted-private.pem
edc_model_form/tests/etc/user-rsa-restricted-public.pem
edc_model_form/tests/etc/user-salt-local.key
edc_model_form/tests/etc/user-salt-restricted.key
edc_model_form/tests/tests/__init__.py
edc_model_form/tests/tests/test_estimated_from_ago.py
edc_model_form-1.0.0.dist-info/AUTHORS
edc_model_form-1.0.0.dist-info/LICENSE
edc_model_form-1.0.0.dist-info/METADATA
edc_model_form-1.0.0.dist-info/WHEEL
edc_model_form-1.0.0.dist-info/top_level.txt
edc_model_form-1.0.0.dist-info/RECORD
